gtnapi/__init__.py
gtnapi/_auth.py
gtnapi/_connection.py
gtnapi/_requests.py
gtnapi/_shared.py
gtnapi/_streaming.py
gtnapi-0.0.6.dist-info/LICENSE
gtnapi-0.0.6.dist-info/METADATA
gtnapi-0.0.6.dist-info/WHEEL
gtnapi-0.0.6.dist-info/entry_points.txt
gtnapi-0.0.6.dist-info/top_level.txt
gtnapi-0.0.6.dist-info/RECORD
