Metadata-Version: 2.2
Name: gtnapi
Version: 0.0.6
Summary: Python Software Developement Kit for GTN Fintech API
Author-email: Uditha Nagahawatta <n.uditha@gtngroup.com>
Maintainer-email: Fintech API Team <fintechapi-dev@gtngroup.com>
License: MIT License
Project-URL: Homepage, https://github.com/gtn/python-sdk.git
Project-URL: Download, https://github.com/gtn/python-sdk.git/releases
Project-URL: Documentation, https://github.com/gtn/python-sdk.git/README.md
Project-URL: Source, https://github.com/gtn/python-sdk.git
Keywords: GTN API
Classifier: Development Status :: 4 - Beta
Classifier: License :: OSI Approved :: Apache Software License
Classifier: Programming Language :: Python :: 3
Classifier: Programming Language :: Python :: 3.9
Classifier: Programming Language :: Python :: 3.10
Classifier: Programming Language :: Python :: 3.11
Classifier: Programming Language :: Python :: 3.12
Classifier: Programming Language :: Python :: 3.13
Classifier: Operating System :: OS Independent
Classifier: Topic :: Internet
Classifier: Topic :: Software Development :: Libraries :: Python Modules
Classifier: Intended Audience :: Developers
Requires-Python: >=3.10
License-File: LICENSE
Requires-Dist: requests
Requires-Dist: cryptography
Requires-Dist: PyJWT
Requires-Dist: websocket-client
Provides-Extra: test
Requires-Dist: pytest; extra == "test"
Requires-Dist: websockets; extra == "test"
Provides-Extra: optional
Requires-Dist: python-socks; extra == "optional"
Requires-Dist: wsaccel; extra == "optional"
Provides-Extra: docs
Requires-Dist: Sphinx>=6.0; extra == "docs"
Requires-Dist: sphinx_rtd_theme>=1.1.0; extra == "docs"
Requires-Dist: myst-parser>=2.0.0; extra == "docs"
